[
  {
    "titulo": "Ministério da Educação/Universidade Tecnológica Federal do Paraná",
    "texto": "nomear, em caráter efetivo, de acordo com os artigos 9º e 10 da Lei nº 8.112, de 11 de dezembro de 1990, para o cargo de Professor do Magistério Superior, na denominação Adjunto A, Classe A, Nível 1, em regime de trabalho de Dedicação Exclusiva, DIEGO ANTONIO CUSTODIO, habilitado em concurso público, homologado através do Edital nº 06/2025, publicado no D.O.U. de 29 de janeiro de 2025, para o Campus Curitiba, na vaga nº 0919567, oriunda da vacância de Fernando Oliveira de Andrade.</p><p class=\"assina\">EVERTON RICARDI LOZANO DA SILVA</p>",
    "assinatura": 12
  },
  {
    "titulo": "Ministério da Educação/Fundação Universidade Federal do Rio Grande/Reitoria",
    "texto": "Nomear, em caráter efetivo, VANESSA DE QUADROS MARTINS, em virtude de habilitação em concurso público de provas e títulos, instituído pelo Edital nº 12, publicado no DOU em 07/08/2023, homologado pelo Edital nº 3, publicado no DOU em 03/04/2024, e de acordo com o inciso I do art. 9º da Lei nº 8.112, de 11 de dezembro de 1990, art. 8º da Lei nº 12.772, de 28 de dezembro de 2012, e Lei nº 12.863, de 24 de setembro de 2013, para o cargo de Professor do Magistério Superior, Adjunto-A, Classe A, Nível 1, com Doutorado, em regime de trabalho de 40 horas semanais, com Dedicação Exclusiva, com exercício no Instituto de Ciências Econômicas, Administrativas e Contábeis (ICEAC), para atuar no campus de Rio Grande/RS, código da vaga nº 319037, conforme Processo nº 23116.008862/2023-83. A posse ocorrerá no prazo de 30 dias, contados da publicação deste ato no DOU.</p><p class=\"assina\">SUZANE DA ROCHA VIEIRA GONÇALVES</p>",
    "assinatura": 12
  }
]